{
  "task_id": "excelxr_001",
  "task_dir_name": "excelxr_001_board_action_register_from_minutes_packet_and_aliases_seed",
  "doc_type": "excel",
  "primary_modality": "Excel (.xlsx)",
  "atomic_operations": [
    "C1 Extraction",
    "C5 Reasoning",
    "S2 Reorder",
    "S4 Table/Sheet ops"
  ],
  "num_atomic_operations": 4,
  "composition_type": "cross-document",
  "composition_pattern": "rebuild-two-live-sheets -> fill-dual-trackers -> restore-dashboard-formulas -> preserve-validations-and-cf",
  "difficulty": "Very Hard",
  "source_type": "Cross-document document-ops V7 realworld",
  "input_path": "/root/excelxr_001_board_action_register_from_minutes_packet_and_aliases_seed.xlsx",
  "supporting_input_paths": [
    "/root/board_packet_extract.pdf",
    "/root/decision_note.docx",
    "/root/owner_map.xlsx"
  ],
  "output_path": "/root/submission/excelxr_001_board_action_register_from_minutes_packet_and_aliases_seed.xlsx",
  "output_filename": "excelxr_001_board_action_register_from_minutes_packet_and_aliases_seed.xlsx",
  "output_extension": ".xlsx",
  "output_kind": "document",
  "verifier_mode": "semantic-strict",
  "user_task_description": "Populate only the blank rows of the `Decision Register` sheet with motion ID.",
  "single_step_benchmark_instruction": "Populate only the blank rows of the `Decision Register` sheet with motion ID, agenda item, normalized owner, due date, and packet-support section from the meeting materials. Then move `Decision Register` directly after `Cover` without altering formulas, styles, or other sheets.",
  "atomic_scope": "Only the two live sheets, both template sheets, the dashboard formulas, workbook names, and highlighted late rows are required.",
  "expected_output_type": "A revised .xlsx artifact that completes the requested cross-document document operation.",
  "notes": {
    "Task Notes": "- Keep the template sheets unchanged\n- Do not replace formulas with hardcoded text"
  }
}
